naver_bs/__init__.py
naver_bs/rules.py
naver_bs/workflow.py
test/__init__.py
test/naver_getprops.py
test/naver_netval.py
test/naver_param.py
test/naver_query.py
test/naver_userpermission.py
test/naver_write.py
test/naver_writelog.py
naver_bs-0.0.1.dist-info/METADATA
naver_bs-0.0.1.dist-info/WHEEL
naver_bs-0.0.1.dist-info/top_level.txt
naver_bs-0.0.1.dist-info/RECORD
