Metadata-Version: 2.1
Name: naver-bs
Version: 0.0.1
Summary: A Business Ancestor Library
Home-page: https://github.com/jacr6/naver-db
Author: Jose Cuevas
Author-email: jose.cuevas.cv@gmail.com
License: UNKNOWN
Platform: UNKNOWN
Classifier: Programming Language :: Python :: 3
Classifier: License :: OSI Approved :: MIT License
Classifier: Operating System :: OS Independent
Requires-Dist: numpy
Requires-Dist: pandas
Requires-Dist: naver-config
Requires-Dist: SpiffWorkflow
